LICENSE-APACHE
LICENSE-MIT
MANIFEST.in
README.rst
setup.cfg
setup.py
greetpustat/__init__.py
greetpustat/__main__.py
greetpustat/extractlink.py
greetpustat/greet.py
greetpustat.egg-info/PKG-INFO
greetpustat.egg-info/SOURCES.txt
greetpustat.egg-info/dependency_links.txt
greetpustat.egg-info/entry_points.txt
greetpustat.egg-info/requires.txt
greetpustat.egg-info/top_level.txt
tests/__init__.py